{
  "name": "小西康陽",
  "sortName": "コニシヤスハル",
  "tracks": [
    {
      "id": "41a1b046-bc07-4f37-80f6-28c607524f09",
      "title": "クイズの女王",
      "artist": "SMAP",
      "isrc": "JPVI00525260",
      "releaseDate": "2005-07-27",
      "spotifyUrl": "",
      "isFallback": false
    },
    {
      "id": "30ca44c3-f009-4533-9ee6-4db3a320b0d1",
      "title": "メッセージ・ソング",
      "artist": "ピチカート・ファイブ",
      "isrc": "JPCO09649420",
      "releaseDate": "1996-12-21",
      "spotifyUrl": "https://open.spotify.com/track/5OoVWtlDOIuFqfBDXS7ASW",
      "isFallback": true
    },
    {
      "id": "08ca293e-a3ce-4032-b86f-2b6c866fd0fb",
      "title": "Mon Amour Tokyo (Mon Amour Kyotokyo mix)",
      "artist": "Pizzicato Five",
      "isrc": "",
      "releaseDate": "1998",
      "spotifyUrl": "",
      "isFallback": false
    },
    {
      "id": "1466802d-9d76-4a61-adec-6735f1198dc0",
      "title": "Martin & James",
      "artist": "Pizzicato Five",
      "isrc": "",
      "releaseDate": "1996-11-22",
      "spotifyUrl": "",
      "isFallback": false
    },
    {
      "id": "246b935b-e510-47ec-995f-444132209163",
      "title": "Fortune Cookie",
      "artist": "Pizzicato Five",
      "isrc": "JPCO09428270",
      "releaseDate": "1995-10-31",
      "spotifyUrl": "https://open.spotify.com/track/6SSrMG1tbGVGbx1M9RVPI7",
      "isFallback": true
    },
    {
      "id": "1257b2c0-5c4f-4bd2-87ab-5fb9bab17fba",
      "title": "日曜はダメよ",
      "artist": "三浦理恵子",
      "isrc": "JPPC09101380",
      "releaseDate": "1991-11-07",
      "spotifyUrl": "https://open.spotify.com/track/4GmaNM9ORD9wW0UGS4haUr",
      "isFallback": true
    },
    {
      "id": "cafa5fd7-427b-411d-81b9-65d767c6d555",
      "title": "CDJ (english version)",
      "artist": "Pizzicato Five",
      "isrc": "",
      "releaseDate": "1995-10-31",
      "spotifyUrl": "",
      "isFallback": false
    },
    {
      "id": "575832d1-7380-4858-a9da-e2bb9b89bfaf",
      "title": "優しい木曜日",
      "artist": "Pizzicato Five",
      "isrc": "JPCO09315100",
      "releaseDate": "1993-06-01",
      "spotifyUrl": "https://open.spotify.com/track/4489bWV4U2hQ6qaMsabzAP",
      "isFallback": true
    },
    {
      "id": "a3c25e01-5fdb-4f04-bc8d-67facee820c7",
      "title": "クエスチョンズ",
      "artist": "Pizzicato Five",
      "isrc": "JPCO09432830",
      "releaseDate": "1994-10-01",
      "spotifyUrl": "https://open.spotify.com/track/0681fsgpdfkvh8534lAVHO",
      "isFallback": true
    },
    {
      "id": "77c5c272-bf04-4101-a1f8-99af949b39c4",
      "title": "ラメントNo.5",
      "artist": "中山忍",
      "isrc": "JPSR09003330",
      "releaseDate": "1990-08-01",
      "spotifyUrl": "",
      "isFallback": false
    },
    {
      "id": "825bf8a2-fe08-471f-ab60-ea73a160d676",
      "title": "スーパースター",
      "artist": "野宮真貴",
      "isrc": "JPN301101764",
      "releaseDate": "2012-01-25",
      "spotifyUrl": "https://open.spotify.com/track/1qTHZYMwPTVWKDoEXyYWZz",
      "isFallback": true
    },
    {
      "id": "3b7bf7e6-6cf4-41c9-b099-3913bc6bd514",
      "title": "オンナのコ♡オトコのコ",
      "artist": "小倉優子",
      "isrc": "JPKI00409325",
      "releaseDate": "2004-11-26",
      "spotifyUrl": "",
      "isFallback": false
    },
    {
      "id": "a2bf09c6-5ba9-4749-941b-e555786eb533",
      "title": "Snowflakes (extended)",
      "artist": "Pizzicato Five",
      "isrc": "",
      "releaseDate": "1996-11-22",
      "spotifyUrl": "",
      "isFallback": false
    },
    {
      "id": "a7083eb9-98ab-4d98-8184-1cbcd195d1a0",
      "title": "ベイビィ・ポータブル・ロック",
      "artist": "Pizzicato Five",
      "isrc": "JPCO09601700",
      "releaseDate": "1996-03-20",
      "spotifyUrl": "https://open.spotify.com/track/6bEoozuY94YJVuW04LxyPW",
      "isFallback": true
    },
    {
      "id": "74cdd284-d8ff-4b10-bd4b-da16866cfcbb",
      "title": "アイドルばかり聴かないで",
      "artist": "Negicco",
      "isrc": "JPE871300507",
      "releaseDate": "2013-05-29",
      "spotifyUrl": "https://open.spotify.com/track/18fRZ05f5oo3l2dQ7ZiyH6",
      "isFallback": true
    },
    {
      "id": "2cc47148-d0ce-4fe7-8f2c-bd4aa23fec1f",
      "title": "Holger & Marcus",
      "artist": "Pizzicato Five",
      "isrc": "JPCO09618630",
      "releaseDate": "1996-11-22",
      "spotifyUrl": "https://open.spotify.com/track/0jgHLMcixTDyVeWGKw9cVc",
      "isFallback": true
    },
    {
      "id": "f6e485ec-fc68-4aa0-be85-9a9b0c10ed9d",
      "title": "ソフィスティケイテッド・キャッチー",
      "artist": "Pizzicato Five",
      "isrc": "JPCO09315240",
      "releaseDate": "1993-06-01",
      "spotifyUrl": "",
      "isFallback": false
    },
    {
      "id": "ed1e241e-3cc1-4fb9-bf68-d688229e0bf7",
      "title": "女王陛下よ永遠なれ",
      "artist": "Pizzicato Five",
      "isrc": "JPSR08909430",
      "releaseDate": "1989-07-21",
      "spotifyUrl": "",
      "isFallback": false
    },
    {
      "id": "9320b53c-9eff-42b9-9116-92b6d55a0dae",
      "title": "My Baby Portable Player Sound (High Llamas remix)",
      "artist": "Pizzicato Five",
      "isrc": "",
      "releaseDate": "1998-05-05",
      "spotifyUrl": "",
      "isFallback": false
    },
    {
      "id": "afca5e71-f6e2-41ef-85b1-a71bc2569516",
      "title": "ルート246",
      "artist": "深田恭子＆ザ・ツートーンズ",
      "isrc": "JPPC00200289",
      "releaseDate": "2002-05-22",
      "spotifyUrl": "https://open.spotify.com/track/012FZQ7EZqvH0oOavG3Hmm",
      "isFallback": true
    },
    {
      "id": "68da2e87-9876-433b-b6b2-15a865a35f9c",
      "title": "Porno 3003",
      "artist": "Pizzicato Five",
      "isrc": "JPCO09721090",
      "releaseDate": "1997-06-21",
      "spotifyUrl": "",
      "isFallback": false
    },
    {
      "id": "7b9d5022-6314-44df-a1d8-2a419a59160d",
      "title": "ゴーゴー女王陛下",
      "artist": "Pizzicato Five",
      "isrc": "",
      "releaseDate": "1989-07-21",
      "spotifyUrl": "",
      "isFallback": false
    },
    {
      "id": "88a8f81c-5970-4438-866f-d5ddc3482e1e",
      "title": "Levenslang",
      "artist": "Jan Rot",
      "isrc": "NLM551200036",
      "releaseDate": "2012",
      "spotifyUrl": "https://open.spotify.com/track/3pnNy1c6penQcSHVVJhZd4",
      "isFallback": true
    },
    {
      "id": "3e5827ed-ae35-4fe7-8bb5-940aa02a77ce",
      "title": "It’s a Beautiful Day (The B‐Day arrangement)",
      "artist": "Pizzicato Five",
      "isrc": "",
      "releaseDate": "1997",
      "spotifyUrl": "",
      "isFallback": false
    },
    {
      "id": "94e4e6be-f188-40ba-b1db-c0074d9ced8a",
      "title": "ストロベリィ・スレイライド",
      "artist": "Pizzicato Five",
      "isrc": "JPCO09315040",
      "releaseDate": "1995-10-31",
      "spotifyUrl": "https://open.spotify.com/track/1lAmObmXfLxXeIxGlgcemX",
      "isFallback": true
    },
    {
      "id": "d0fd5941-21f4-42bd-9494-cd7d60877fb0",
      "title": "Theme of 015",
      "artist": "SMAP",
      "isrc": "JPVI00226690",
      "releaseDate": "2002-07-24",
      "spotifyUrl": "",
      "isFallback": false
    },
    {
      "id": "8f974253-21fd-4c55-907f-1995757b57ae",
      "title": "マジック・カーペット・ライド",
      "artist": "Pizzicato Five",
      "isrc": "JPCO01925660",
      "releaseDate": "1995-03-01",
      "spotifyUrl": "https://open.spotify.com/track/7gpOsHMNKYur5k8cS7NuP0",
      "isFallback": true
    },
    {
      "id": "a9cefb76-343a-489f-af4f-d1cd781d8252",
      "title": "Number Five (Lament No. 5)",
      "artist": "Pizzicato Five",
      "isrc": "",
      "releaseDate": "1995-10-31",
      "spotifyUrl": "",
      "isFallback": false
    },
    {
      "id": "4b92546e-d851-4936-aa3c-c5b6f7a0edb9",
      "title": "We Love Pizzicato Five",
      "artist": "Pizzicato Five",
      "isrc": "JPCO09501690",
      "releaseDate": "1995-10-31",
      "spotifyUrl": "https://open.spotify.com/track/6QFKk5wS5aSVWqav8OvLTj",
      "isFallback": true
    },
    {
      "id": "eaef3d65-6d8d-4470-a8d9-9d1b55cd8460",
      "title": "悲しい歌",
      "artist": "野宮真貴",
      "isrc": "JPN301101770",
      "releaseDate": "2012-01-25",
      "spotifyUrl": "https://open.spotify.com/track/6dQGs6Hg8JyTCc6NgDp8jz",
      "isFallback": true
    },
    {
      "id": "79c5540f-01b9-44e1-a699-6fb0fd20201f",
      "title": "世界中でいちばんきれいな女の子",
      "artist": "Pizzicato Five",
      "isrc": "JPCO09432760",
      "releaseDate": "1994-10-01",
      "spotifyUrl": "https://open.spotify.com/track/05IeI5qdg7y0OTGsgJMI5x",
      "isFallback": true
    },
    {
      "id": "8bd4452d-cc13-4e52-9e0d-32767710d82b",
      "title": "Airplane ’96",
      "artist": "Pizzicato Five",
      "isrc": "JPCO09618580",
      "releaseDate": "1996-06-21",
      "spotifyUrl": "",
      "isFallback": false
    },
    {
      "id": "92bd694c-5853-4a68-89cc-02013af681d4",
      "title": "新ベリッシマ",
      "artist": "Pizzicato Five",
      "isrc": "JPSR08909290",
      "releaseDate": "1989-07-21",
      "spotifyUrl": "",
      "isFallback": false
    },
    {
      "id": "44039999-cc71-4d94-baf3-ca61dcc3df49",
      "title": "Readymade FM",
      "artist": "Pizzicato Five",
      "isrc": "JPCO09432820",
      "releaseDate": "1994-10-01",
      "spotifyUrl": "",
      "isFallback": false
    },
    {
      "id": "3e5abd9f-e456-4969-8905-24bb6a39e87a",
      "title": "恋のテレビジョン・エイジ",
      "artist": "Pizzicato Five",
      "isrc": "JPSR08909300",
      "releaseDate": "1989-07-21",
      "spotifyUrl": "",
      "isFallback": false
    },
    {
      "id": "6334157c-7041-41e1-bbf3-2952f6fc855c",
      "title": "スーパースター",
      "artist": "Pizzicato Five",
      "isrc": "JPCO09428260",
      "releaseDate": "1994-07-21",
      "spotifyUrl": "https://open.spotify.com/track/0HmBMb0ALqjDU597PQicbz",
      "isFallback": true
    },
    {
      "id": "438a0f82-044c-46d6-9904-b29e5f80abaa",
      "title": "Overture",
      "artist": "Pizzicato Five",
      "isrc": "JPCO09433130",
      "releaseDate": "1994-10-01",
      "spotifyUrl": "",
      "isFallback": false
    },
    {
      "id": "9b5df140-7d16-4712-b147-618498a71efd",
      "title": "Collision and Improvisation (Dizzy Fugu mix)",
      "artist": "Pizzicato Five",
      "isrc": "",
      "releaseDate": "1998-01-21",
      "spotifyUrl": "",
      "isFallback": false
    },
    {
      "id": "326925b7-8923-41e0-bfce-e4da381d27a4",
      "title": "ショッピング・バッグ",
      "artist": "Pizzicato Five",
      "isrc": "JPCO09432720",
      "releaseDate": "1994-10-01",
      "spotifyUrl": "https://open.spotify.com/track/76pa3qgQTf7AoNJh7oTu8X",
      "isFallback": true
    },
    {
      "id": "128a931c-90e2-42f2-930c-063c862f99ee",
      "title": "Trailer Music (808 State remix)",
      "artist": "Pizzicato Five",
      "isrc": "",
      "releaseDate": "1997-10-07",
      "spotifyUrl": "",
      "isFallback": false
    },
    {
      "id": "d1172a89-2228-49bf-89a2-4f94d95e4d96",
      "title": "Happy Sad",
      "artist": "Pizzicato Five",
      "isrc": "JPCO09409270",
      "releaseDate": "1994-10-01",
      "spotifyUrl": "https://open.spotify.com/track/11u7DJ4Hq27KCUV2L4Fy40",
      "isFallback": true
    },
    {
      "id": "4fe2973a-fa33-4a69-bb8c-bed4e524dbbc",
      "title": "ふなっしーの買い物わっしょい!",
      "artist": "ふなっしー",
      "isrc": "JPPO01407803",
      "releaseDate": "2014-08-20",
      "spotifyUrl": "https://open.spotify.com/track/0BrGWQBWgABGLkd9tpVOb8",
      "isFallback": true
    },
    {
      "id": "0772dcee-79bf-4f14-b053-aafabbc9dc5a",
      "title": "カーマイン・ローション",
      "artist": "松本伊代",
      "isrc": "JPVI09008520",
      "releaseDate": "1991-01-21",
      "spotifyUrl": "https://open.spotify.com/track/3aeboH4iWqAdWIRe73zt3T",
      "isFallback": true
    },
    {
      "id": "6ead0bbf-d44e-4490-8758-9c52a12874cc",
      "title": "Love’s Theme (Automator mix)",
      "artist": "Pizzicato Five",
      "isrc": "",
      "releaseDate": "1997",
      "spotifyUrl": "",
      "isFallback": false
    },
    {
      "id": "b53dd18e-e7a2-45a3-87f5-a37cc6209660",
      "title": "恋の呪文はパパピプパ",
      "artist": "小倉優子",
      "isrc": "JPKI00409326",
      "releaseDate": "2004-11-26",
      "spotifyUrl": "",
      "isFallback": false
    },
    {
      "id": "9bb334e4-94a2-466a-9119-02d883558800",
      "title": "スウィート・ソウル・レヴュー",
      "artist": "Pizzicato Five",
      "isrc": "JPCO09304690",
      "releaseDate": "2001-12-21",
      "spotifyUrl": "https://open.spotify.com/track/4QOeo7TtiJntEz9oehagTV",
      "isFallback": true
    },
    {
      "id": "7923216a-68ca-4b9a-a15d-3c3e13094caa",
      "title": "ショコラに夢中",
      "artist": "野本かりあ",
      "isrc": "JPKI00505938",
      "releaseDate": "2005-08-03",
      "spotifyUrl": "",
      "isFallback": false
    },
    {
      "id": "b2335667-41f4-47ed-8b05-31586dca5ce3",
      "title": "Happy Ending (If Then Else mix)",
      "artist": "Pizzicato Five",
      "isrc": "",
      "releaseDate": "1997",
      "spotifyUrl": "",
      "isFallback": false
    },
    {
      "id": "3f979f97-bd58-43b1-a709-c637eb6ce7ec",
      "title": "乙女のススメ",
      "artist": "ちびうさ",
      "isrc": "JPKI01612180",
      "releaseDate": "2016-05-25",
      "spotifyUrl": "https://open.spotify.com/track/3XvHNSLv9duZWEsROpQ24Z",
      "isFallback": true
    },
    {
      "id": "a549bc7e-163e-4723-bd1c-7f147aea1d4b",
      "title": "V・A・C・A・T・I・O・N",
      "artist": "吉村由美",
      "isrc": "JPES09700824",
      "releaseDate": "1997-07-09",
      "spotifyUrl": "https://open.spotify.com/track/3pmr61yfV8JaRikGudug8I",
      "isFallback": true
    },
    {
      "id": "9a2b377c-4664-44a4-a7cd-468825aed0bf",
      "title": "Airplane",
      "artist": "Pizzicato Five",
      "isrc": "JPCO09432770",
      "releaseDate": "1994-10-01",
      "spotifyUrl": "https://open.spotify.com/track/0BFmRWaW4IcUe2uyQwxWr5",
      "isFallback": true
    },
    {
      "id": "42239abd-fb70-4376-b04b-fe443b93fbcb",
      "title": "Domino (instrumental)",
      "artist": "Pizzicato Five",
      "isrc": "",
      "releaseDate": "1996-11-22",
      "spotifyUrl": "",
      "isFallback": false
    },
    {
      "id": "0ec5c381-e934-466a-a90b-32c122f4915f",
      "title": "The World Is Spinning at 45 RPM (Sunroof mix edit)",
      "artist": "Pizzicato Five",
      "isrc": "",
      "releaseDate": "1998-05-05",
      "spotifyUrl": "",
      "isFallback": false
    },
    {
      "id": "cf65bf92-9cd4-4476-b806-098a47d9e9b1",
      "title": "ロックン・ロール",
      "artist": "Pizzicato Five",
      "isrc": "JPCO09315060",
      "releaseDate": "1995-10-31",
      "spotifyUrl": "",
      "isFallback": false
    },
    {
      "id": "1545afbe-8b32-4ad2-b519-7b0d52171f7d",
      "title": "⋯好きです",
      "artist": "芳賀ゆい",
      "isrc": "JPSR09067309",
      "releaseDate": "1990-08-01",
      "spotifyUrl": "",
      "isFallback": false
    },
    {
      "id": "d0409b58-c079-455f-be9b-d7c77e500f5e",
      "title": "ヒッピー・デイ",
      "artist": "Pizzicato Five",
      "isrc": "JPCO09432790",
      "releaseDate": "1994-10-01",
      "spotifyUrl": "https://open.spotify.com/track/1t8ItvQ3pvZP8rym3XBQjt",
      "isFallback": true
    },
    {
      "id": "ad14f54a-77a6-492d-89c4-eb1cadf43e4a",
      "title": "To Our Children’s Children’s Children",
      "artist": "Pizzicato Five",
      "isrc": "JPCO09618650",
      "releaseDate": "1996-11-22",
      "spotifyUrl": "https://open.spotify.com/track/1U4FLrQdeb5GXscS3b9yaZ",
      "isFallback": true
    },
    {
      "id": "9aee5d99-967c-44c7-bf3f-17f8cafb8974",
      "title": "我が名はグルーヴィー",
      "artist": "Pizzicato Five",
      "isrc": "JPCO09315230",
      "releaseDate": "1993-06-01",
      "spotifyUrl": "https://open.spotify.com/track/02iF4uWtjpEnKWUVTRR6va",
      "isFallback": true
    },
    {
      "id": "5422cee8-5436-46bf-8457-371d3d5c4d69",
      "title": "キミノヒトミニコイシテル",
      "artist": "深田恭子",
      "isrc": "JPPC00101087",
      "releaseDate": "2001-10-03",
      "spotifyUrl": "https://open.spotify.com/track/4hdEQV80htIN3gmoqO1alO",
      "isFallback": true
    },
    {
      "id": "a8898161-fa76-4043-b351-58914f4ed69d",
      "title": "大都会交響楽",
      "artist": "Pizzicato Five",
      "isrc": "JPCO09751350",
      "releaseDate": "1997-12-10",
      "spotifyUrl": "https://open.spotify.com/track/562oxI3WO6Vc9XDswOY4vN",
      "isFallback": true
    },
    {
      "id": "c43609b1-01ae-41dd-a1a7-3ac82f0bc702",
      "title": "Itsuwari No Koi -Ai No (L'Amour)",
      "artist": "カヒミ・カリィ",
      "isrc": "JPPS09502740",
      "releaseDate": "1995-07-26",
      "spotifyUrl": "https://open.spotify.com/track/20PhVN0kFbWIqosTcbLKHt",
      "isFallback": true
    },
    {
      "id": "6551ba84-7724-43be-8c5e-7f4e497b46a9",
      "title": "Sugar Pie Honey Bunch Marching Band",
      "artist": "鈴木雅之",
      "isrc": "JPU901900456",
      "releaseDate": "2019-03-13",
      "spotifyUrl": "https://open.spotify.com/track/7ladNlXw7pyyuWIXdyBMjw",
      "isFallback": true
    },
    {
      "id": "b710fb2c-2d80-4dca-ac34-8a5f08ce5ec6",
      "title": "72",
      "artist": "新しい地図 join ミュージック",
      "isrc": "JPWP02200154",
      "releaseDate": "2017-12-24",
      "spotifyUrl": "https://open.spotify.com/track/6BgntwVzVfhuLg5vNe1RWm",
      "isFallback": true
    },
    {
      "id": "3dfab5b2-bf57-431e-9f9b-08022c424872",
      "title": "「女王陛下のエロチカ大作戦」からの抜粋〜a.ナイロビの女王陛下",
      "artist": "Pizzicato Five",
      "isrc": "JPSR08909330",
      "releaseDate": "1989-07-21",
      "spotifyUrl": "",
      "isFallback": false
    },
    {
      "id": "6a6c8823-dfc0-4aac-8a95-b802c6af276e",
      "title": "交通渋滞",
      "artist": "松本伊代",
      "isrc": "JPVI09008500",
      "releaseDate": "1991-01-21",
      "spotifyUrl": "https://open.spotify.com/track/1ihfHEJwwnX3NtP36F6YAt",
      "isFallback": true
    },
    {
      "id": "a2e72de1-4707-4666-b327-dd19529a6313",
      "title": "少しだけ遠くに",
      "artist": "松本伊代",
      "isrc": "JPVI08801110",
      "releaseDate": "1989-01-21",
      "spotifyUrl": "https://open.spotify.com/track/4AkenooLFZmbGglnMMIBna",
      "isFallback": true
    },
    {
      "id": "79e2d64e-350f-4676-aa2a-99950bc9915a",
      "title": "お久しぶりです・お元気ですか",
      "artist": "Negicco",
      "isrc": "JPZ922304924",
      "releaseDate": "2023-07-20",
      "spotifyUrl": "https://open.spotify.com/track/6sglpX5sRiSpK3UBCV7BVG",
      "isFallback": false
    },
    {
      "id": "52fb80ee-dad9-4531-8b0b-45797be57607",
      "title": "衛星中継",
      "artist": "Pizzicato Five",
      "isrc": "JPSR08909410",
      "releaseDate": "1989-07-21",
      "spotifyUrl": "",
      "isFallback": false
    },
    {
      "id": "da6c6260-48d9-487d-b17d-61407d9c648b",
      "title": "Statue of Liberty",
      "artist": "Pizzicato Five",
      "isrc": "JPCO09432740",
      "releaseDate": "1994-10-01",
      "spotifyUrl": "",
      "isFallback": false
    },
    {
      "id": "305091db-95ac-43bb-ad5f-ea229dc36eaf",
      "title": "東京は夜の七時",
      "artist": "Pizzicato Five",
      "isrc": "JPCO09348320",
      "releaseDate": "1993-12-01",
      "spotifyUrl": "https://open.spotify.com/track/0JhYO042gz7lBj98SCTM5P",
      "isFallback": true
    },
    {
      "id": "879d0b83-90ac-4b91-b93d-94a1fc4b172a",
      "title": "On the Sunny Side of the Street",
      "artist": "Pizzicato Five",
      "isrc": "JPCO09432690",
      "releaseDate": "1994-10-01",
      "spotifyUrl": "https://open.spotify.com/track/5sKcnKSG99NlP0mahUAwx8",
      "isFallback": true
    },
    {
      "id": "40e1df2c-b68c-4cc9-8727-89f895fddc0a",
      "title": "有給休暇",
      "artist": "松本伊代",
      "isrc": "JPVI08801070",
      "releaseDate": "1989-01-21",
      "spotifyUrl": "https://open.spotify.com/track/1L3hwRoWnSGPZTuMmPVaiF",
      "isFallback": true
    },
    {
      "id": "acc0ab7f-90cb-44bb-b258-79c6542ac076",
      "title": "涙のピチカート",
      "artist": "中山忍",
      "isrc": "",
      "releaseDate": "1990-08-01",
      "spotifyUrl": "",
      "isFallback": false
    }
  ]
}
