{
  "name": "黒須克彦",
  "sortName": "クロスカツヒコ",
  "tracks": [
    {
      "id": "27307e89-c6e7-4219-9822-a8f91619add7",
      "title": "Unnamed world",
      "artist": "平野綾",
      "isrc": "JPI100800692",
      "releaseDate": "2008-04-23",
      "spotifyUrl": "https://open.spotify.com/track/6lEQVZIrANlhP2OmB4VdJL",
      "isFallback": true
    },
    {
      "id": "291de81f-767c-479d-a3fa-2e9bbc375851",
      "title": "Hazy",
      "artist": "スフィア",
      "isrc": "JPI101100743",
      "releaseDate": "2011-05-11",
      "spotifyUrl": "https://open.spotify.com/track/4qo73tMA978gcPhuV5KxFH",
      "isFallback": true
    },
    {
      "id": "b2978779-c4f0-4890-a40e-7be309f86631",
      "title": "Let it shine",
      "artist": "内田彩",
      "isrc": "JPS231300092",
      "releaseDate": "2015-07-22",
      "spotifyUrl": "https://open.spotify.com/track/7rXRKWtLtYaUC3A4o6EIfW",
      "isFallback": true
    },
    {
      "id": "837fac7e-ee6d-4b02-9f1a-0b2367e20e5e",
      "title": "Brand New Smile",
      "artist": "高垣彩陽",
      "isrc": "JPX401100362",
      "releaseDate": "2012-02-08",
      "spotifyUrl": "https://open.spotify.com/track/3PDCfG7SXEDyGVOQsiWiAw",
      "isFallback": true
    },
    {
      "id": "506208f3-f13f-4f1a-8140-0ad1503e0839",
      "title": "for...",
      "artist": "逢田梨香子",
      "isrc": "JPJ221901346",
      "releaseDate": "2019-10-05",
      "spotifyUrl": "https://open.spotify.com/track/7uh6tzwLtqX4VIZORcb67P",
      "isFallback": true
    },
    {
      "id": "ed768a5a-5170-4bea-9c3d-669d5427526e",
      "title": "Secret of sensation",
      "artist": "涼宮ハルヒ",
      "isrc": "JPI101000148",
      "releaseDate": "2010-02-24",
      "spotifyUrl": "https://open.spotify.com/track/1Fnt3V9AwYbcWIozJ54oay",
      "isFallback": true
    },
    {
      "id": "f2522f94-e38b-4006-a8c9-19ad29fb7fd6",
      "title": "Chocolate Party!",
      "artist": "やなせなつみ",
      "isrc": "",
      "releaseDate": "2005-05-25",
      "spotifyUrl": "",
      "isFallback": false
    },
    {
      "id": "20663792-a026-4377-8e51-d9a5b3e21f40",
      "title": "I can’t live without you.",
      "artist": "田所あずさ",
      "isrc": "JPI101701974",
      "releaseDate": "2017-10-25",
      "spotifyUrl": "https://open.spotify.com/track/7J1xnGNkbion6udWcyJXRg",
      "isFallback": true
    },
    {
      "id": "5f192b01-ba39-4bcb-9685-401a74377a77",
      "title": "START!",
      "artist": "mao",
      "isrc": "JPV200990107",
      "releaseDate": "2010-07-07",
      "spotifyUrl": "https://open.spotify.com/track/6VoBMOPbzxSgVRrJTJdSN8",
      "isFallback": true
    },
    {
      "id": "aad7a93f-3c10-43ea-8270-ff0b21efc104",
      "title": "Brilliant Ways",
      "artist": "島谷ひとみ",
      "isrc": "JPB601902184",
      "releaseDate": "2019-07-24",
      "spotifyUrl": "https://open.spotify.com/track/1uriWBEIPNTGq4L0aK0Zwg",
      "isFallback": false
    },
    {
      "id": "a081ddae-0ede-4871-baa8-1c428bc55dd5",
      "title": "LOVE★GUN",
      "artist": "平野綾",
      "isrc": "JPI100701921",
      "releaseDate": "2007-10-10",
      "spotifyUrl": "https://open.spotify.com/track/6xyhBeXh9i245RfjWt4WAJ",
      "isFallback": true
    },
    {
      "id": "46b1a468-8b8a-49cf-a583-4b5d584d086b",
      "title": "Starting STYLE!!",
      "artist": "ランティスのみんな",
      "isrc": "",
      "releaseDate": "2014-09-10",
      "spotifyUrl": "",
      "isFallback": false
    },
    {
      "id": "ede33deb-eb35-4e39-9009-9ff67ea579fa",
      "title": "Oh my holiday !",
      "artist": "南條愛乃",
      "isrc": "JPPI01600740",
      "releaseDate": "2016-07-13",
      "spotifyUrl": "https://open.spotify.com/track/6gYjqHoiUkxwY2aWw4T7Vb",
      "isFallback": true
    },
    {
      "id": "28ace198-3ce1-4de4-9d1f-ee997096b2c1",
      "title": "PARTY☆ビート",
      "artist": "Trignal",
      "isrc": "JPI101202748",
      "releaseDate": "2012-12-12",
      "spotifyUrl": "https://open.spotify.com/track/1EHAyYr0bygkOksKffX3vt",
      "isFallback": true
    },
    {
      "id": "1fdaa6fa-f0c9-481c-870e-565353264064",
      "title": "Such a beautiful affair",
      "artist": "神谷浩史",
      "isrc": "JPI101202338",
      "releaseDate": "2012-10-31",
      "spotifyUrl": "https://open.spotify.com/track/5eoEGPPDUsO2iAURQGdzw9",
      "isFallback": true
    },
    {
      "id": "a15042e9-a380-4a3c-aff4-dad2de0f4f63",
      "title": "Growing UP!",
      "artist": "アスクール",
      "isrc": "JPI100902905",
      "releaseDate": "2009-12-09",
      "spotifyUrl": "",
      "isFallback": false
    },
    {
      "id": "3287d3d3-386c-452d-8210-8355835f3cf9",
      "title": "happily ever after",
      "artist": "中川翔子",
      "isrc": "JPSR00701222",
      "releaseDate": "2007-06-27",
      "spotifyUrl": "https://open.spotify.com/track/2AWWmkqtMrIlPt7B8Gif0k",
      "isFallback": true
    },
    {
      "id": "a43f4aef-554f-45f2-8fab-c8c463cc34ff",
      "title": "SING MY SONG",
      "artist": "最上静香",
      "isrc": "JPI101702128",
      "releaseDate": "2017-10-25",
      "spotifyUrl": "https://open.spotify.com/track/56GP0ABA4d9kXMn6as9AES",
      "isFallback": false
    },
    {
      "id": "f6dd057d-c2a4-4f47-9e8c-db11de0d6c43",
      "title": "Velvet Tears",
      "artist": "藍井エイル",
      "isrc": "JPU901201681",
      "releaseDate": "2012-11-21",
      "spotifyUrl": "https://open.spotify.com/track/5EBoWSetlVdEhQGpKmaDKp",
      "isFallback": true
    },
    {
      "id": "ce841ecf-025b-4725-9f13-08d8148388af",
      "title": "calling location",
      "artist": "中川翔子",
      "isrc": "JPSR00800462",
      "releaseDate": "2008-03-19",
      "spotifyUrl": "https://open.spotify.com/track/5cb3Ls0JOpvAHYtf0sHUnn",
      "isFallback": true
    },
    {
      "id": "f452adb2-8e4d-473f-9cf8-9e84a62da547",
      "title": "dear‐dear DREAM",
      "artist": "マイサンシャイン",
      "isrc": "JPI100900989",
      "releaseDate": "2009-06-03",
      "spotifyUrl": "",
      "isFallback": false
    },
    {
      "id": "c361ef26-668c-48b2-95eb-dee0ec9fc0b3",
      "title": "Good Luck",
      "artist": "アリス",
      "isrc": "JPP301700453",
      "releaseDate": "2007-03-21",
      "spotifyUrl": "https://open.spotify.com/track/5yFsRIPotgL3tyZD637NiB",
      "isFallback": true
    },
    {
      "id": "11e39c02-ba61-4e5d-9db5-5dcf2285f9c3",
      "title": "Little Promise",
      "artist": "栗林みな実",
      "isrc": "JPI100900564",
      "releaseDate": "2009-04-22",
      "spotifyUrl": "https://open.spotify.com/track/5StNnUKaGauiLxCUD9oQZ7",
      "isFallback": true
    },
    {
      "id": "29ccda3d-2b1f-4d3d-a77f-6463239cfee4",
      "title": "HEAT:Moment",
      "artist": "橋本みゆき",
      "isrc": "JPI101803072",
      "releaseDate": "2019-01-23",
      "spotifyUrl": "https://open.spotify.com/track/0Sd1b0bBINCCZzQZD6Ggq9",
      "isFallback": true
    },
    {
      "id": "1a7d7b75-f213-4d6f-be82-9e7ac62623e5",
      "title": "Swimming with words",
      "artist": "SSGIRLS",
      "isrc": "JPPI02451410",
      "releaseDate": "2024-07-10",
      "spotifyUrl": "https://open.spotify.com/track/1YRXYGmuUt65axPauYeUoq",
      "isFallback": true
    },
    {
      "id": "3177f9bd-cad6-40df-ab19-f7c077ab96a9",
      "title": "to be continued",
      "artist": "雪ノ下雪乃",
      "isrc": "JPPI02450000",
      "releaseDate": "2024-02-16",
      "spotifyUrl": "https://open.spotify.com/track/2m5ya1FRmL1HUzPgrVkCbz",
      "isFallback": true
    },
    {
      "id": "789b6ceb-87bf-4d5c-b5b8-3155ccdb772c",
      "title": "Found Me",
      "artist": "川村ゆみ",
      "isrc": "JPE300800723",
      "releaseDate": "2008-07-02",
      "spotifyUrl": "",
      "isFallback": false
    },
    {
      "id": "fae088ce-ff34-4059-9798-ee2a65d8d5f6",
      "title": "Possible!",
      "artist": "新田恵海",
      "isrc": "JPW672200004",
      "releaseDate": "2022-12-07",
      "spotifyUrl": "https://open.spotify.com/track/5ncSjsHP6WJqEvBplSWhlk",
      "isFallback": true
    },
    {
      "id": "88c49150-5ed2-4240-854f-33746aed6e83",
      "title": "Crimson Eyes",
      "artist": "藍井エイル",
      "isrc": "JPU901200591",
      "releaseDate": "2012-04-11",
      "spotifyUrl": "https://open.spotify.com/track/5inof0KIoiMYX9rdQsBb0y",
      "isFallback": true
    },
    {
      "id": "e6af5261-5574-48f8-97b1-824c3c2cd374",
      "title": "disarm dreamer",
      "artist": "美郷あき",
      "isrc": "JPI100702188",
      "releaseDate": "2007-10-24",
      "spotifyUrl": "https://open.spotify.com/track/0ZBIpO1t7ByXmQWkOXC5lj",
      "isFallback": true
    },
    {
      "id": "8a38700b-af77-43b9-9565-928b4a387bbd",
      "title": "I lost the place",
      "artist": "美郷あき",
      "isrc": "JPI100800276",
      "releaseDate": "2008-03-12",
      "spotifyUrl": "https://open.spotify.com/track/2tvUiQbEe0bSD4vUR4H8YU",
      "isFallback": true
    },
    {
      "id": "44bcb4e0-8236-4551-a4d2-88180615ceb1",
      "title": "Rock’n Life",
      "artist": "AiRI",
      "isrc": "JPI101102175",
      "releaseDate": "2011-11-09",
      "spotifyUrl": "",
      "isFallback": false
    },
    {
      "id": "874e1621-0acc-4372-bcea-cf35a1548d87",
      "title": "Simple feelings",
      "artist": "南條愛乃",
      "isrc": "JPPI01600590",
      "releaseDate": "2016-05-25",
      "spotifyUrl": "https://open.spotify.com/track/5F8rGyDG271fN84kfrZiZQ",
      "isFallback": true
    },
    {
      "id": "623752e6-f2e5-4fab-ac9f-8419441a8cb7",
      "title": "アイシテ!",
      "artist": "平野綾",
      "isrc": "JPI100901460",
      "releaseDate": "2009-07-22",
      "spotifyUrl": "https://open.spotify.com/track/1ZfECb36jpfBMworgV1MkT",
      "isFallback": true
    },
    {
      "id": "3d3333f2-9edc-4056-af9b-985f68b2ad92",
      "title": "Blood Queen",
      "artist": "美郷あき",
      "isrc": "JPI100700510",
      "releaseDate": "2008-04-23",
      "spotifyUrl": "https://open.spotify.com/track/2l9Ckjvhk9W3wSWM6BQOCK",
      "isFallback": true
    },
    {
      "id": "4572ff20-7473-4e62-8485-708d4843ecd9",
      "title": "feel it",
      "artist": "美郷あき",
      "isrc": "JPI100701244",
      "releaseDate": "2007-08-08",
      "spotifyUrl": "https://open.spotify.com/track/17Ak9BQM8V4tMLx1UCXep8",
      "isFallback": true
    },
    {
      "id": "302e587e-2349-4b83-a6ec-bf7a17d49c26",
      "title": "Win-possible!",
      "artist": "Trignal",
      "isrc": "JPI101301561",
      "releaseDate": "2013-07-31",
      "spotifyUrl": "https://open.spotify.com/track/058t8WisRdrJPsHCdO6nG3",
      "isFallback": true
    },
    {
      "id": "273e1ecf-e5b6-47a4-bb7e-8e9378b114bd",
      "title": "Cheer Up!",
      "artist": "橋本みゆき",
      "isrc": "JPI100401648",
      "releaseDate": "2005-01-13",
      "spotifyUrl": "https://open.spotify.com/track/2OtsT2GIuij8alOwm2vhwA",
      "isFallback": true
    },
    {
      "id": "d948b937-9395-4101-874e-3e9449943677",
      "title": "We can do it !!",
      "artist": "中川翔子",
      "isrc": "JPSR00800463",
      "releaseDate": "2008-03-19",
      "spotifyUrl": "https://open.spotify.com/track/3MtQNZqgQNR6pBVQLF7Deq",
      "isFallback": true
    },
    {
      "id": "cba97825-6c02-4520-8dfc-8d073a82fe24",
      "title": "Time Flies",
      "artist": "SSGIRLS",
      "isrc": "JPPI02451400",
      "releaseDate": "2024-07-10",
      "spotifyUrl": "https://open.spotify.com/track/7pLyn43shFQZZ0z0BShKjs",
      "isFallback": true
    },
    {
      "id": "a3e32d6f-c81c-4f23-b0d7-a586563f17d1",
      "title": "Memories",
      "artist": "石川由依",
      "isrc": "JPI102001295",
      "releaseDate": "2020-10-21",
      "spotifyUrl": "https://open.spotify.com/track/0DEm5bDgzJhr74hcN09ahY",
      "isFallback": true
    },
    {
      "id": "197769fe-2f3e-409b-86f0-501ed2d37a2d",
      "title": "HAPPY CHERRY FESTA!",
      "artist": "美郷あき",
      "isrc": "JPI100700520",
      "releaseDate": "2007-05-23",
      "spotifyUrl": "https://open.spotify.com/track/7vVHs2whnxmzryGJahGmaw",
      "isFallback": true
    },
    {
      "id": "04cb17ff-2cb8-489a-96a8-d352b2061635",
      "title": "Fly high〜ツバサノキオク〜",
      "artist": "栗林みな実",
      "isrc": "JPI101101737",
      "releaseDate": "2011-09-21",
      "spotifyUrl": "https://open.spotify.com/track/1MRRSfL7mkV7JS0GWoI4rw",
      "isFallback": true
    },
    {
      "id": "c0ad6eb6-4d36-42f7-8e37-1be25574cc74",
      "title": "Love Blossom",
      "artist": "茅原実里",
      "isrc": "JPI101600160",
      "releaseDate": "2016-04-06",
      "spotifyUrl": "https://open.spotify.com/track/7yFOTcpAcGo0IY7xxpTasl",
      "isFallback": true
    },
    {
      "id": "5311804a-aea5-4668-a63a-fde1be2ff3ed",
      "title": "Follow your arrows",
      "artist": "SSGIRLS",
      "isrc": "JPPI02450730",
      "releaseDate": "2024-04-24",
      "spotifyUrl": "https://open.spotify.com/track/2Ya8SUcuyrFno3RxBHbyzb",
      "isFallback": true
    },
    {
      "id": "a8c5c101-a148-46d7-be0d-9e69837653f7",
      "title": "あおぞら",
      "artist": "田所あずさ",
      "isrc": "JPI101401428",
      "releaseDate": "2014-07-30",
      "spotifyUrl": "https://open.spotify.com/track/6JZ2qvbofGDrZGkJPn2Num",
      "isFallback": true
    },
    {
      "id": "1c36e180-4b48-40b7-af05-5a9c02801f0a",
      "title": "Bright Future",
      "artist": "藍井エイル",
      "isrc": "JPU901501649",
      "releaseDate": "2015-05-20",
      "spotifyUrl": "https://open.spotify.com/track/5HQ4DfB5Yq8c4Bj8u8uR21",
      "isFallback": true
    },
    {
      "id": "da4e310b-a388-4cf6-8891-3ecdbe07ace5",
      "title": "When I was in love",
      "artist": "涼宮ハルヒ",
      "isrc": "JPI101000149",
      "releaseDate": "2010-02-24",
      "spotifyUrl": "https://open.spotify.com/track/1lDRg1abhmzniE9m3BZDC8",
      "isFallback": true
    },
    {
      "id": "1cceca62-940a-4f24-b6ab-c663b0109906",
      "title": "EVOLUTiON:",
      "artist": "南條愛乃",
      "isrc": "JPPI02101630",
      "releaseDate": "2021-10-05",
      "spotifyUrl": "https://open.spotify.com/track/1G35je93UC1GUGTzBuDRKK",
      "isFallback": true
    },
    {
      "id": "14aa45da-3f88-4ba8-8d8e-8fbd58604ee3",
      "title": "Raspberry Moon",
      "artist": "藍井エイル",
      "isrc": "JPU901401838",
      "releaseDate": "2014-11-12",
      "spotifyUrl": "https://open.spotify.com/track/1UksXs7fzQh4CcpaknzGXH",
      "isFallback": true
    },
    {
      "id": "178ab3a7-c6ac-4747-9c3e-7ea10624e4b2",
      "title": "Set me free",
      "artist": "平野綾",
      "isrc": "JPI100900559",
      "releaseDate": "2009-04-29",
      "spotifyUrl": "https://open.spotify.com/track/5O9sgFXD8m03J7He1nSMV1",
      "isFallback": true
    },
    {
      "id": "e2733faa-0675-48ed-9bca-b5d99a3a209b",
      "title": "Water Lily",
      "artist": "野中藍",
      "isrc": "",
      "releaseDate": "2006-11-08",
      "spotifyUrl": "",
      "isFallback": false
    },
    {
      "id": "728c3f92-1e48-40b9-8c8c-34aa4c970fe8",
      "title": "Seven Seas Romance",
      "artist": "中川翔子",
      "isrc": "JPSR01400145",
      "releaseDate": "2014-04-02",
      "spotifyUrl": "https://open.spotify.com/track/5L61uAWEqbq1o54NqdVZzA",
      "isFallback": true
    },
    {
      "id": "e45cc5c3-1bac-4500-b1de-74249ad89f33",
      "title": "wintry breeze",
      "artist": "橋本みゆき",
      "isrc": "TCJPM2009088",
      "releaseDate": "2006-05-04",
      "spotifyUrl": "https://open.spotify.com/track/1iRHpCZR5ujwjZdwMfgc0r",
      "isFallback": true
    },
    {
      "id": "45ba0d7d-f917-4822-a03a-7fa5c1841ffa",
      "title": "My First Lesson",
      "artist": "三森すずこ",
      "isrc": "JPPC01601560",
      "releaseDate": "2016-09-07",
      "spotifyUrl": "https://open.spotify.com/track/2LxPloe9atyRJwAKCUw5Yz",
      "isFallback": true
    },
    {
      "id": "749fd335-effa-407a-b548-e2f4d1a8ac4d",
      "title": "resume",
      "artist": "雪ノ下雪乃",
      "isrc": "JPPI02450010",
      "releaseDate": "2024-02-16",
      "spotifyUrl": "https://open.spotify.com/track/51YGfWmq9b3WcAlJ5v26Za",
      "isFallback": true
    },
    {
      "id": "e104b3e8-efe5-4fa9-bfba-a3f526baff03",
      "title": "Sting of Love",
      "artist": "KAmiYU",
      "isrc": "JPI101101276",
      "releaseDate": "2011-08-03",
      "spotifyUrl": "https://open.spotify.com/track/71JE0KtPWbS2CsyPfMHcfv",
      "isFallback": true
    },
    {
      "id": "a1500494-274e-4127-8858-e9347a326c43",
      "title": "purest note～あたたかい音～",
      "artist": "茅原実里",
      "isrc": "JPI101500272",
      "releaseDate": "2015-03-25",
      "spotifyUrl": "https://open.spotify.com/track/7fVSMoavWc15zfmQIB3MCN",
      "isFallback": true
    },
    {
      "id": "f3fd7045-4da1-447b-ae41-64c06c681eed",
      "title": "Canvas boy × Palette girl",
      "artist": "LiSA",
      "isrc": "JPE301302674",
      "releaseDate": "2013-10-30",
      "spotifyUrl": "https://open.spotify.com/track/4CGy2qhEn8wN1eWXBpfbzr",
      "isFallback": true
    },
    {
      "id": "1bcd9a86-f29b-42a7-8eb4-8e9d55161ecf",
      "title": "more than Zero",
      "artist": "神谷浩史",
      "isrc": "JPI102100005",
      "releaseDate": "2021-03-24",
      "spotifyUrl": "https://open.spotify.com/track/0ALk7mbcKRzH8JuhlqUjCn",
      "isFallback": true
    },
    {
      "id": "bff1c2cc-4977-44a5-919f-fe351df6e9ed",
      "title": "idc",
      "artist": "南條愛乃",
      "isrc": "JPPI01600790",
      "releaseDate": "2016-07-13",
      "spotifyUrl": "https://open.spotify.com/track/0bFHqssSasFAUNYtncBkcZ",
      "isFallback": true
    },
    {
      "id": "fe3db75f-6264-43ac-825e-5f66192059a6",
      "title": "spit out",
      "artist": "田所あずさ",
      "isrc": "JPI101601283",
      "releaseDate": "2016-07-06",
      "spotifyUrl": "https://open.spotify.com/track/3peGXvbAbf2fMEHAIiAKwW",
      "isFallback": true
    },
    {
      "id": "77564af2-8412-4af4-9039-51c211fa393f",
      "title": "Colored Memories",
      "artist": "石川由依",
      "isrc": "JPI102001289",
      "releaseDate": "2020-10-21",
      "spotifyUrl": "https://open.spotify.com/track/3mGOrInE7yvIY5FxUWYA7s",
      "isFallback": true
    },
    {
      "id": "361da762-86f7-44e3-84d9-ced91b51c448",
      "title": "Ivy",
      "artist": "中川翔子",
      "isrc": "JPSR00804223",
      "releaseDate": "2009-01-01",
      "spotifyUrl": "https://open.spotify.com/track/1Uq5f5WttOITjbghG4EgJO",
      "isFallback": true
    },
    {
      "id": "9e19fed9-9e53-4088-8bef-af633e6614dc",
      "title": "Lの感情",
      "artist": "由比ヶ浜結衣",
      "isrc": "JPPI02050360",
      "releaseDate": "2020-11-27",
      "spotifyUrl": "https://open.spotify.com/track/1OoFcGarOYAzWDFObOZHgq",
      "isFallback": true
    },
    {
      "id": "0ead055a-89e8-446b-b12a-233bf0c4b217",
      "title": "A.T.M.O.S.P.H.E.R.E",
      "artist": "スフィア",
      "isrc": "JPI100903189",
      "releaseDate": "2009-12-23",
      "spotifyUrl": "https://open.spotify.com/track/3mk5T3qZLhluMBEgTGJBMm",
      "isFallback": true
    },
    {
      "id": "2f86dd78-5b98-430d-9283-14c678deae26",
      "title": "Dream sign",
      "artist": "スフィア",
      "isrc": "JPI100903186",
      "releaseDate": "2009-12-23",
      "spotifyUrl": "https://open.spotify.com/track/00Q56gMWtsEWJ53NUlGQwD",
      "isFallback": true
    },
    {
      "id": "d72707d0-80cb-4f3c-b819-410e8462bfbd",
      "title": "Hello Again",
      "artist": "ネギ・スプリングフィールド",
      "isrc": "JPKI00708152",
      "releaseDate": "2007-09-26",
      "spotifyUrl": "",
      "isFallback": false
    },
    {
      "id": "7aa96ebd-ce4e-4eab-9a15-d0d6c49e76d5",
      "title": "Punkish regular",
      "artist": "涼宮ハルヒ",
      "isrc": "JPI100901919",
      "releaseDate": "2009-09-30",
      "spotifyUrl": "https://open.spotify.com/track/4X7N3qPKWaPUwyus4CW2BB",
      "isFallback": true
    },
    {
      "id": "5fe1436d-9881-4c6e-9db0-f2469d57dc17",
      "title": "NO.1",
      "artist": "2B PENCILS",
      "isrc": "JPPI01354780",
      "releaseDate": "2013-12-11",
      "spotifyUrl": "https://open.spotify.com/track/75iGX79Sf4S8JrAHFCeQdq",
      "isFallback": true
    },
    {
      "id": "e1757f55-fc17-4ae0-ae45-1006a5b7f7a6",
      "title": "Circle-Lets Friends! -Miyuki Hashimoto Ver.-",
      "artist": "橋本みゆき",
      "isrc": "JPI101803077",
      "releaseDate": "2019-01-30",
      "spotifyUrl": "https://open.spotify.com/track/60czDLW5rVbg9eDEOPLF9w",
      "isFallback": true
    },
    {
      "id": "9bc4523c-a7bd-4674-918c-43d4dee4c47a",
      "title": "Hello Alone",
      "artist": "雪ノ下雪乃",
      "isrc": "JPPI01351260",
      "releaseDate": "2013-05-22",
      "spotifyUrl": "https://open.spotify.com/track/0wX0dFABi18A9YV5pBRt0u",
      "isFallback": true
    },
    {
      "id": "8b226663-cd34-4993-ac7a-8078ab1e7206",
      "title": "Strangers",
      "artist": "TRD",
      "isrc": "JPPC02110958",
      "releaseDate": "2021-11-04",
      "spotifyUrl": "https://open.spotify.com/track/0S94H0JHLS3P9C5sgofjIj",
      "isFallback": true
    },
    {
      "id": "a7700182-6890-4c1d-8a21-71b0af16362e",
      "title": "Unusual Days",
      "artist": "美郷あき",
      "isrc": "JPI100802428",
      "releaseDate": "2008-12-25",
      "spotifyUrl": "https://open.spotify.com/track/2CuXA45zaIzgnH3jgjxhM2",
      "isFallback": true
    },
    {
      "id": "356d46bc-9240-4a20-a49d-a2e1571b993a",
      "title": "Miracle a Go! Go!",
      "artist": "中川翔子",
      "isrc": "JPSR01400141",
      "releaseDate": "2014-04-02",
      "spotifyUrl": "https://open.spotify.com/track/1GLdM8EqP3bb9iyKVliRF8",
      "isFallback": true
    },
    {
      "id": "19e63dc1-43d8-404a-8030-165a34f0cd3b",
      "title": "Believe",
      "artist": "TrySail",
      "isrc": "JPU901900327",
      "releaseDate": "2019-02-27",
      "spotifyUrl": "https://open.spotify.com/track/560RfRUUDfkHU70OW7twp9",
      "isFallback": true
    },
    {
      "id": "145c9020-c385-4deb-87db-bc55df1e54d5",
      "title": "an-tiit",
      "artist": "南條愛乃",
      "isrc": "JPPI01900740",
      "releaseDate": "2019-07-24",
      "spotifyUrl": "https://open.spotify.com/track/45DuO5vct5vjHxd76DVXvo",
      "isFallback": true
    },
    {
      "id": "bbebd621-2498-4a8b-95e7-f10b2d8f2ee1",
      "title": "Only you",
      "artist": "Duca",
      "isrc": "USQ4E1300819",
      "releaseDate": "2013-04-23",
      "spotifyUrl": "https://open.spotify.com/track/3MgYETEHApLSVMTtXoneVz",
      "isFallback": true
    },
    {
      "id": "4f60d8e4-c02d-465d-b989-b07ca461495a",
      "title": "Fly together",
      "artist": "yozuca*",
      "isrc": "JPI100401060",
      "releaseDate": "2004-09-01",
      "spotifyUrl": "",
      "isFallback": false
    },
    {
      "id": "65fbf8e8-ecc3-49e9-a7bd-15549223267b",
      "title": "magic hour",
      "artist": "内田真礼",
      "isrc": "JPPC01800374",
      "releaseDate": "2018-04-25",
      "spotifyUrl": "https://open.spotify.com/track/6KTFgT5tZq7wWSFIzYUZx3",
      "isFallback": true
    },
    {
      "id": "8329eafc-8446-4474-af58-83f074e2c15a",
      "title": "For you",
      "artist": "平野綾",
      "isrc": "JPI100801316",
      "releaseDate": "2008-07-16",
      "spotifyUrl": "https://open.spotify.com/track/3EQ4NHgpwuWZvqsb8fo0Lc",
      "isFallback": true
    },
    {
      "id": "b953713f-6a47-4820-9279-5f04b263d682",
      "title": "TryAgain",
      "artist": "TrySail",
      "isrc": "JPU901900326",
      "releaseDate": "2019-02-27",
      "spotifyUrl": "https://open.spotify.com/track/6qzGl3TMpepKOcF83LjXgg",
      "isFallback": true
    },
    {
      "id": "afe1d25b-adb4-41c7-ada4-208a5541edd6",
      "title": "Treasures!!",
      "artist": "スフィア",
      "isrc": "JPI100900704",
      "releaseDate": "2009-04-22",
      "spotifyUrl": "https://open.spotify.com/track/4GOci65V7UbNiwtOtN0ONa",
      "isFallback": true
    },
    {
      "id": "c8233048-5327-452d-bbc1-3650939c2020",
      "title": "Eternal Tours",
      "artist": "スフィア",
      "isrc": "JPI101400122",
      "releaseDate": "2014-02-26",
      "spotifyUrl": "https://open.spotify.com/track/7mBQMieS7089A7ctKjBwsl",
      "isFallback": true
    },
    {
      "id": "ef039fe3-ca9a-450e-a704-dd0f218e427c",
      "title": "Dangerous girls",
      "artist": "スフィア",
      "isrc": "JPI100901325",
      "releaseDate": "2009-07-29",
      "spotifyUrl": "https://open.spotify.com/track/2zxkUR69B0muXldv3u856p",
      "isFallback": true
    },
    {
      "id": "84c6d373-24cc-4eb5-a70c-9d130ba42d11",
      "title": "Reverb",
      "artist": "内田彩",
      "isrc": "JPCO02001950",
      "releaseDate": "2020-02-14",
      "spotifyUrl": "https://open.spotify.com/track/1WkwcJ36zgQOuq8oYbtldj",
      "isFallback": false
    },
    {
      "id": "c73f2214-a39b-4a15-aa0d-c0b325e87b3e",
      "title": "MonStAR",
      "artist": "平野綾",
      "isrc": "JPI100702408",
      "releaseDate": "2007-12-05",
      "spotifyUrl": "https://open.spotify.com/track/37TypnLhppbJJUOM03g0Rb",
      "isFallback": true
    },
    {
      "id": "a05fe5be-25c3-4959-a42a-d7919bd20da3",
      "title": "Sunny Spot",
      "artist": "SSGIRLS",
      "isrc": "JPPI02451390",
      "releaseDate": "2024-07-10",
      "spotifyUrl": "https://open.spotify.com/track/7kZnJn0TejtzvkvWsAOFfu",
      "isFallback": true
    },
    {
      "id": "bb8b8cab-c561-4df4-95b8-86d7871b2d87",
      "title": "Destiny",
      "artist": "橋本みゆき",
      "isrc": "TCJPM2009092",
      "releaseDate": "2006-05-04",
      "spotifyUrl": "https://open.spotify.com/track/3hc6bifyShurwiv70i3Sj1",
      "isFallback": true
    },
    {
      "id": "7288740f-ddc5-49ce-bcd0-23bc6b75c3fe",
      "title": "Baby universe day",
      "artist": "アスクール",
      "isrc": "JPI100902793",
      "releaseDate": "2009-11-25",
      "spotifyUrl": "",
      "isFallback": false
    },
    {
      "id": "4faa0e00-e900-4b8b-9211-9c2d439ab938",
      "title": "Bitter Bitter Sweet",
      "artist": "雪ノ下雪乃",
      "isrc": "JPPI01352910",
      "releaseDate": "2013-07-10",
      "spotifyUrl": "https://open.spotify.com/track/7M9NqUCN83HnjSIQxYZSVG",
      "isFallback": true
    },
    {
      "id": "86e8e186-e2e0-4cef-8ba8-1d3be6e59179",
      "title": "INTENTION",
      "artist": "鈴村健一",
      "isrc": "JPI100801927",
      "releaseDate": "2009-09-09",
      "spotifyUrl": "https://open.spotify.com/track/3RuJwilk14pqtnSpzLO8ve",
      "isFallback": true
    },
    {
      "id": "8b2ac7e4-63b4-4fd0-8524-4243c1a538e9",
      "title": "Precious days",
      "artist": "三森すずこ",
      "isrc": "JPPC01900039",
      "releaseDate": "2019-02-20",
      "spotifyUrl": "https://open.spotify.com/track/2pfcklCPc1Re2Cm5gTxLa6",
      "isFallback": true
    },
    {
      "id": "2d390b37-1ea5-40c8-809f-db2c044bd8af",
      "title": "Holiday",
      "artist": "内田彩",
      "isrc": "JPS231700025",
      "releaseDate": "2017-09-13",
      "spotifyUrl": "https://open.spotify.com/track/7pbs6csyx1vNYb4om4YcP7",
      "isFallback": true
    },
    {
      "id": "a139f175-0ad9-4ecf-94fe-e2e33e87d602",
      "title": "Maybe I can't good-bye.",
      "artist": "平野綾",
      "isrc": "JPI100800693",
      "releaseDate": "2008-04-23",
      "spotifyUrl": "https://open.spotify.com/track/4DBFm4fx1oefIr1QGmHo9C",
      "isFallback": true
    },
    {
      "id": "976d448c-0262-42cc-bf92-4b7e1b8b0dff",
      "title": "Love and Fate",
      "artist": "カンノユウキ",
      "isrc": "JPD640800133",
      "releaseDate": "2008-05-21",
      "spotifyUrl": "",
      "isFallback": false
    },
    {
      "id": "cc74006c-979c-4a16-9a94-cf487c326ee7",
      "title": "Sing a Song!",
      "artist": "平野綾",
      "isrc": "JPI100900560",
      "releaseDate": "2009-04-29",
      "spotifyUrl": "https://open.spotify.com/track/4XzXPMfcz7H3h3kQvk3BiQ",
      "isFallback": true
    },
    {
      "id": "b6cded95-af7c-4317-b24f-c89f5699252b",
      "title": "Oh, Love & Peace!",
      "artist": "μ's",
      "isrc": "JPI101201618",
      "releaseDate": "2012-09-05",
      "spotifyUrl": "https://open.spotify.com/track/2gA4V4ord962OQFXnUozUz",
      "isFallback": true
    },
    {
      "id": "b0fac692-eace-4ade-91e8-07e72efcb83a",
      "title": "REALOVE:REALIFE",
      "artist": "スフィア",
      "isrc": "JPI101000478",
      "releaseDate": "2010-04-21",
      "spotifyUrl": "https://open.spotify.com/track/08Hysu7k8GiBrUpcU1Fs6V",
      "isFallback": true
    },
    {
      "id": "2558fa54-114e-4302-91bd-73a2f7d6990d",
      "title": "Made in WONDER",
      "artist": "美郷あき",
      "isrc": "JPI100901517",
      "releaseDate": "2009-08-05",
      "spotifyUrl": "https://open.spotify.com/track/3kjTYUOuyrNQWJgChkpt9E",
      "isFallback": true
    },
    {
      "id": "1d6eaeb4-a2a2-4021-967b-5b2d480bbdf3",
      "title": "曖昧スクリーム",
      "artist": "平野綾",
      "isrc": "JPI100801314",
      "releaseDate": "2008-07-16",
      "spotifyUrl": "https://open.spotify.com/track/1SRLj7C4bVUzcxc84QweT6",
      "isFallback": true
    },
    {
      "id": "1ce23b36-4cde-461c-b4d3-e14771f634a7",
      "title": "グラン・シャリオ",
      "artist": "ELISA",
      "isrc": "JPU901603421",
      "releaseDate": "2016-11-30",
      "spotifyUrl": "https://open.spotify.com/track/0AzZzIYLza3qnPB3Hr8ufe",
      "isFallback": true
    },
    {
      "id": "2cbbf428-59e0-41a7-9e3b-990341ada20b",
      "title": "ねこ中",
      "artist": "Prima Porta",
      "isrc": "JPW672000024",
      "releaseDate": "2020-07-22",
      "spotifyUrl": "https://open.spotify.com/track/6VqPdkAN2qZNvdxtdT7nV5",
      "isFallback": true
    },
    {
      "id": "49a30e46-872d-465b-840c-b6e9cec96c86",
      "title": "秘密を聞いてよ",
      "artist": "富士葵",
      "isrc": "JPR502146255",
      "releaseDate": "2021-03-16",
      "spotifyUrl": "https://open.spotify.com/track/6Mng09621S55M4nHFpAAxR",
      "isFallback": true
    },
    {
      "id": "a5810093-35a4-473e-8e50-ab1787a4bc15",
      "title": "星を求めて",
      "artist": "結城アイラ",
      "isrc": "JPI101001667",
      "releaseDate": "2012-11-21",
      "spotifyUrl": "https://open.spotify.com/track/1N0BfphuftNZj7bsQib9g8",
      "isFallback": true
    },
    {
      "id": "b5c8f5cd-0d3c-4cc6-9ee2-5e7d7876c6a1",
      "title": "ノスタルジア",
      "artist": "小野大輔",
      "isrc": "JPI100700908",
      "releaseDate": "2007-06-27",
      "spotifyUrl": "https://open.spotify.com/track/4qUds4dc0nzuELdj8pnO0N",
      "isFallback": true
    },
    {
      "id": "a38d3ff5-9c58-421c-bf51-e0c0945e2a17",
      "title": "ビビッドナイトフィーバー！",
      "artist": "寺島拓篤",
      "isrc": "JPI101501999",
      "releaseDate": "2015-11-18",
      "spotifyUrl": "https://open.spotify.com/track/5Hd6z5WKsALsBURLZuLUnR",
      "isFallback": true
    },
    {
      "id": "05e4557e-4547-4451-b77b-18db693f35eb",
      "title": "ハッピーエンドのそばで",
      "artist": "由比ヶ浜結衣",
      "isrc": "JPPI01554530",
      "releaseDate": "2015-12-29",
      "spotifyUrl": "https://open.spotify.com/track/09azSoSCrkOYsjkM1OIJ29",
      "isFallback": true
    },
    {
      "id": "37794fc3-b3ac-403e-a37f-70b790b98035",
      "title": "硝子のSunshine",
      "artist": "クローバー",
      "isrc": "JPI100501179",
      "releaseDate": "2005-07-21",
      "spotifyUrl": "",
      "isFallback": false
    },
    {
      "id": "51863995-9dab-42f8-a24c-485dce46f987",
      "title": "ツインテールはもうしない",
      "artist": "まゆ",
      "isrc": "JPSR01202246",
      "releaseDate": "2012-07-25",
      "spotifyUrl": "https://open.spotify.com/track/119nYiAfTYiDNKZVF3y3wS",
      "isFallback": true
    },
    {
      "id": "4887af64-f5a0-49c3-92ab-f218fc029ef0",
      "title": "つまさきだち",
      "artist": "伊藤かな恵",
      "isrc": "JPI101100762",
      "releaseDate": "2011-05-25",
      "spotifyUrl": "https://open.spotify.com/track/2zNsYQxVSPKcKFE0mdkIkl",
      "isFallback": true
    },
    {
      "id": "843ef0ec-cc39-474e-b631-84a5bd86968a",
      "title": "もう愛しかいらない",
      "artist": "美郷あき",
      "isrc": "JPI100602779",
      "releaseDate": "2007-01-24",
      "spotifyUrl": "https://open.spotify.com/track/7HJxefNjykWp9KQj2e23RQ",
      "isFallback": true
    },
    {
      "id": "1d2d6f7f-6950-4b03-80a4-e278c2e92b6b",
      "title": "風が鳴いている",
      "artist": "yozuca*",
      "isrc": "JPI100401061",
      "releaseDate": "2004-09-01",
      "spotifyUrl": "",
      "isFallback": false
    },
    {
      "id": "beeea294-f99c-4c63-ad38-5876dc9f4e45",
      "title": "クロスファイア",
      "artist": "内田真礼",
      "isrc": "JPPC01602710",
      "releaseDate": "2017-01-11",
      "spotifyUrl": "https://open.spotify.com/track/58jVtitiPYycXPjh9t6rq2",
      "isFallback": true
    },
    {
      "id": "4134af16-56de-467f-b6bc-b300016c5855",
      "title": "シリアス",
      "artist": "内田彩",
      "isrc": "JPS231300130",
      "releaseDate": "2016-02-10",
      "spotifyUrl": "https://open.spotify.com/track/2Ruq0M1zgS6ak6gYHQd4zr",
      "isFallback": true
    },
    {
      "id": "c6a892f2-fe1a-4123-bc91-35db82ed6118",
      "title": "カッコ悪い I love you!",
      "artist": "フレンチ・キス",
      "isrc": "JPB601123201",
      "releaseDate": "2011-05-11",
      "spotifyUrl": "https://open.spotify.com/track/2MTxc98soh0BFrQXDU0n4P",
      "isFallback": true
    },
    {
      "id": "b5a29d1e-6af5-43ed-89e4-70421daa79ae",
      "title": "永遠に咲く花",
      "artist": "橋本みゆき",
      "isrc": "JPI100700907",
      "releaseDate": "2007-06-27",
      "spotifyUrl": "",
      "isFallback": false
    },
    {
      "id": "f42f611e-1063-475a-89ee-a99f29531064",
      "title": "いまの君が遠くても",
      "artist": "美郷あき",
      "isrc": "JPI100702189",
      "releaseDate": "2007-10-24",
      "spotifyUrl": "https://open.spotify.com/track/2VeBYdMRsKo8whqdbWAGeE",
      "isFallback": true
    },
    {
      "id": "9a7fd925-3b1e-41a1-9fce-952701a7d9ae",
      "title": "キラメク",
      "artist": "yozuca*",
      "isrc": "JPI100600819",
      "releaseDate": "2006-04-26",
      "spotifyUrl": "",
      "isFallback": false
    },
    {
      "id": "ce4dc54f-fb4d-4264-ba1e-5e83baf6ffef",
      "title": "始まりは何度でも",
      "artist": "ささきいさお",
      "isrc": "",
      "releaseDate": "2016-09-28",
      "spotifyUrl": "",
      "isFallback": false
    },
    {
      "id": "6e727a80-96dd-4eee-bb7d-5d51b9bedda0",
      "title": "いつだって青空",
      "artist": "茅原実里",
      "isrc": "JPI102102988",
      "releaseDate": "2021-11-18",
      "spotifyUrl": "https://open.spotify.com/track/6RrurDAOC7H9r1CVUOpH9J",
      "isFallback": true
    },
    {
      "id": "5810c63a-4682-4ea0-98ea-de6bf2211057",
      "title": "夏が終わっちゃう",
      "artist": "空野葵",
      "isrc": "JPA601200182",
      "releaseDate": "2012-06-13",
      "spotifyUrl": "https://open.spotify.com/track/5fgN2NfmCKynVJKvdjfsgX",
      "isFallback": true
    },
    {
      "id": "9d016e73-faf4-4472-9729-de699c6bfab3",
      "title": "花とミツバチ",
      "artist": "LiSA",
      "isrc": "JPE301200085",
      "releaseDate": "2012-02-22",
      "spotifyUrl": "https://open.spotify.com/track/7eY3PMFTYi5mplW1pkIrJJ",
      "isFallback": true
    },
    {
      "id": "43c99a55-eced-4bc0-9a26-41bbccc7bf6b",
      "title": "涙の種、笑顔の花",
      "artist": "中川翔子",
      "isrc": "JPSR00900641",
      "releaseDate": "2009-04-29",
      "spotifyUrl": "https://open.spotify.com/track/7bEVE2RiMggZjiXEMB6aUR",
      "isFallback": true
    },
    {
      "id": "5d7615f6-8b40-46d7-98f8-1830f8234eb8",
      "title": "ビリビリ",
      "artist": "yozuca*",
      "isrc": "JPI101700226",
      "releaseDate": "2017-03-22",
      "spotifyUrl": "",
      "isFallback": false
    },
    {
      "id": "d85151f6-49a0-4605-9579-50179291cff5",
      "title": "かってな成長期",
      "artist": "スフィア",
      "isrc": "JPI101001059",
      "releaseDate": "2010-07-28",
      "spotifyUrl": "https://open.spotify.com/track/2Vqv5xbfMtXHDPEWNo2xIE",
      "isFallback": true
    },
    {
      "id": "46573f96-1e82-454a-8ef7-6df838bc51d6",
      "title": "未来へススメ!",
      "artist": "ももいろクローバー",
      "isrc": "JPA250940111",
      "releaseDate": "2009-11-11",
      "spotifyUrl": "https://open.spotify.com/track/1wIn0p0fugcG7WOzO8BnjG",
      "isFallback": true
    },
    {
      "id": "b859253c-902c-453c-8103-fe413bf2ed1e",
      "title": "ダーリンベイビ",
      "artist": "中川かのん",
      "isrc": "JPPI01150040",
      "releaseDate": "2011-03-03",
      "spotifyUrl": "https://open.spotify.com/track/4t9o23Cmr7lU2Bd95OkJmi",
      "isFallback": true
    },
    {
      "id": "062785e6-fe15-4c33-b994-6b53b756ad54",
      "title": "エブリデイワールド",
      "artist": "雪ノ下雪乃",
      "isrc": "JPPI01551230",
      "releaseDate": "2015-06-03",
      "spotifyUrl": "https://open.spotify.com/track/5glSSrrnDdeBCghSp8MLbl",
      "isFallback": true
    },
    {
      "id": "272682ec-7a41-4ee4-a13b-8b0c1062725c",
      "title": "水たまり",
      "artist": "平野綾",
      "isrc": "JPI100902665",
      "releaseDate": "2009-11-18",
      "spotifyUrl": "https://open.spotify.com/track/2rcFFdZSDsCSK57Lz6j42I",
      "isFallback": true
    },
    {
      "id": "6ce9860b-f0a6-40b9-96e3-b5aadd6400cb",
      "title": "最新Dream",
      "artist": "クローバー",
      "isrc": "JPI100500689",
      "releaseDate": "2005-05-25",
      "spotifyUrl": "",
      "isFallback": false
    },
    {
      "id": "0c9ce762-e421-40ad-8c88-c2d90a320905",
      "title": "コズミックジェットコースター",
      "artist": "LiSA",
      "isrc": "JPE301302675",
      "releaseDate": "2013-10-30",
      "spotifyUrl": "https://open.spotify.com/track/7z4kZkNnocfZW1t5d77iU6",
      "isFallback": true
    },
    {
      "id": "fdd292a8-94e9-4123-8616-854455a63b48",
      "title": "青空の見える丘で",
      "artist": "橋本みゆき",
      "isrc": "JPI100601607",
      "releaseDate": "2007-06-27",
      "spotifyUrl": "",
      "isFallback": false
    },
    {
      "id": "37c20a45-2784-4859-b195-f51c64fc302c",
      "title": "あの花のように",
      "artist": "平野綾",
      "isrc": "JPI100902666",
      "releaseDate": "2009-11-18",
      "spotifyUrl": "https://open.spotify.com/track/0XHmzBH5RNLIOiFyKDPc5g",
      "isFallback": true
    },
    {
      "id": "29dcbbbe-2d19-4ccc-8f60-a6d4c9a11be0",
      "title": "ふたつの鼓動と赤い罪 (TV-size)",
      "artist": "ON/OFF",
      "isrc": "",
      "releaseDate": "2008-06-25",
      "spotifyUrl": "",
      "isFallback": false
    },
    {
      "id": "82c35563-79c2-448c-bb6e-e2322fe8b9b7",
      "title": "ココにいる。",
      "artist": "mao",
      "isrc": "JPV201090014",
      "releaseDate": "2010-07-07",
      "spotifyUrl": "https://open.spotify.com/track/5iaYoQcsIk0V6JyQgP68Wb",
      "isFallback": true
    },
    {
      "id": "c3297b3d-4c94-45fa-acc6-e50968668a1b",
      "title": "ふたり",
      "artist": "茅原実里",
      "isrc": "JPI101600163",
      "releaseDate": "2016-04-06",
      "spotifyUrl": "https://open.spotify.com/track/4DdSt2edxgBFlKFKNN915G",
      "isFallback": true
    },
    {
      "id": "474ca857-43a3-4908-964f-a3a215e259ee",
      "title": "最後の旅",
      "artist": "美郷あき",
      "isrc": "JPI101100169",
      "releaseDate": "2011-02-23",
      "spotifyUrl": "https://open.spotify.com/track/6VN6jYWr9Ib1maR7SOliHV",
      "isFallback": true
    },
    {
      "id": "d951be43-08c1-4e07-8582-943d8f2dd082",
      "title": "それは僕たちの奇跡",
      "artist": "μ's",
      "isrc": "JPI101400781",
      "releaseDate": "2014-04-23",
      "spotifyUrl": "https://open.spotify.com/track/4M1msELaGptV81LDVIHAwb",
      "isFallback": true
    },
    {
      "id": "81cbb488-11e8-41ed-af62-bf9751d8bdb9",
      "title": "奇跡",
      "artist": "茅原実里",
      "isrc": "JPI101802232",
      "releaseDate": "2018-08-26",
      "spotifyUrl": "https://open.spotify.com/track/12YSBqFhy8gKh5iYsSlL8a",
      "isFallback": true
    },
    {
      "id": "cd3d7934-0daa-42a9-be5e-d6266c1b22d4",
      "title": "夕焼けノスタルジア",
      "artist": "LiSA",
      "isrc": "JPE301302181",
      "releaseDate": "2013-08-07",
      "spotifyUrl": "https://open.spotify.com/track/1C1ERUdD58aMNHW6MGWZ1T",
      "isFallback": true
    },
    {
      "id": "690646e2-c428-4b8e-b070-8fe65f200295",
      "title": "本気メキメキ♥トキメキメキ",
      "artist": "アテナ&ロビケロッツ",
      "isrc": "JPA600700252",
      "releaseDate": "2007-11-14",
      "spotifyUrl": "https://open.spotify.com/track/2DaeXVoYnPFcOyKNWJVWSs",
      "isFallback": true
    },
    {
      "id": "1cd2d1be-0f86-4410-9f7f-efd7fe33d3f9",
      "title": "綺麗な夢のその果てに",
      "artist": "玖我なつき",
      "isrc": "JPI100500168",
      "releaseDate": "2005-02-23",
      "spotifyUrl": "https://open.spotify.com/track/5kkZLfQgqUWsC6Xe2BvAZH",
      "isFallback": true
    },
    {
      "id": "03de9c91-abf0-4a06-adfd-83f0faa85c51",
      "title": "わからない果実たち",
      "artist": "クローバー",
      "isrc": "JPI100602325",
      "releaseDate": "2006-12-06",
      "spotifyUrl": "",
      "isFallback": false
    },
    {
      "id": "c3b61e7b-8a40-4712-b09f-086732db7f91",
      "title": "微熱S.O.S!!",
      "artist": "橋本みゆき",
      "isrc": "JPI100700471",
      "releaseDate": "2007-04-25",
      "spotifyUrl": "https://open.spotify.com/track/7KuBXH7n0KPqQhDrp3tBzC",
      "isFallback": true
    },
    {
      "id": "876c7711-7474-43e6-89ca-35d81696632a",
      "title": "花痕 -shirushi-",
      "artist": "河野マリナ",
      "isrc": "JPE301401037",
      "releaseDate": "2014-10-22",
      "spotifyUrl": "https://open.spotify.com/track/4wlDpzf4KksdCEo9uDYJ7d",
      "isFallback": true
    },
    {
      "id": "5b3b3340-145d-4b0e-9a07-c442d3078009",
      "title": "ラブソング",
      "artist": "平野綾",
      "isrc": "JPI100702409",
      "releaseDate": "2007-12-05",
      "spotifyUrl": "https://open.spotify.com/track/6wvsMb0hmQwsQjY5R0mnlR",
      "isFallback": true
    },
    {
      "id": "bccf1fb3-8a36-4fd6-b5e4-d4d17f020c0f",
      "title": "ラッパ練習中",
      "artist": "渡辺麻友",
      "isrc": "JPSR01300941",
      "releaseDate": "2013-07-10",
      "spotifyUrl": "https://open.spotify.com/track/68Ei3Ljbj5opNRfDNL3Ca1",
      "isFallback": true
    },
    {
      "id": "7b1198bf-696e-48fa-9869-09c3407f9e53",
      "title": "ヨロコビの歌",
      "artist": "平野綾",
      "isrc": "JPI100601604",
      "releaseDate": "2006-09-06",
      "spotifyUrl": "https://open.spotify.com/track/6ntG0SBaWmHSn0Z45Naefj",
      "isFallback": true
    },
    {
      "id": "4617fb52-9922-4986-8d0a-7b2f78088466",
      "title": "七色の空",
      "artist": "Duca",
      "isrc": "",
      "releaseDate": "2011-09-10",
      "spotifyUrl": "",
      "isFallback": false
    },
    {
      "id": "9e8ac7af-356f-49af-a2b0-c974720477c5",
      "title": "あした天気になあれ",
      "artist": "Duca",
      "isrc": "",
      "releaseDate": "2008-09-30",
      "spotifyUrl": "",
      "isFallback": false
    },
    {
      "id": "b251464b-f208-4dc2-a003-d6dc10f38bcd",
      "title": "ひとひらの願い",
      "artist": "茅原実里",
      "isrc": "JPI101202246",
      "releaseDate": "2012-10-24",
      "spotifyUrl": "https://open.spotify.com/track/4gPOmN60XJ9vuXqgN6GTgy",
      "isFallback": true
    },
    {
      "id": "46e3095c-c0f2-4165-8305-4e7de59186a0",
      "title": "パンドラ",
      "artist": "緒方恵美",
      "isrc": "JPI102100813",
      "releaseDate": "2021-04-21",
      "spotifyUrl": "https://open.spotify.com/track/34zCVCzIU27njMVD9HlLLq",
      "isFallback": true
    },
    {
      "id": "cc0324e1-cb95-4903-8f86-9fb766842325",
      "title": "アストラル",
      "artist": "藍井エイル",
      "isrc": "JPU901301338",
      "releaseDate": "2014-01-29",
      "spotifyUrl": "https://open.spotify.com/track/3bUaAKTLcStxcKkQUC9Tmc",
      "isFallback": true
    },
    {
      "id": "95bc3178-56e3-46b3-9a27-5d25ce3615ca",
      "title": "黒鉄将軍シュバルツ",
      "artist": "シュバルツ将軍",
      "isrc": "JPCO01420710",
      "releaseDate": "2014-12-03",
      "spotifyUrl": "https://open.spotify.com/track/1ZweOMKec9oc0PvCleE9Yk",
      "isFallback": true
    },
    {
      "id": "aef7a28a-aa95-4947-ac84-04267cc113ba",
      "title": "星が永遠を照らしてる",
      "artist": "結城アイラ",
      "isrc": "JPI101200900",
      "releaseDate": "2012-06-27",
      "spotifyUrl": "https://open.spotify.com/track/7vL1v7BbFGFZpdvqWjFGcQ",
      "isFallback": true
    },
    {
      "id": "5e30e31a-8698-46f4-9b0c-62db2e0cb31f",
      "title": "ここから、これから。",
      "artist": "サリヤ人",
      "isrc": "JPI100802427",
      "releaseDate": "2008-12-25",
      "spotifyUrl": "",
      "isFallback": false
    },
    {
      "id": "a4428d3e-0f41-478e-8b69-fbf97aac359d",
      "title": "ムシウタ",
      "artist": "赤月",
      "isrc": "",
      "releaseDate": "2007-07-27",
      "spotifyUrl": "",
      "isFallback": false
    },
    {
      "id": "428a5395-cebc-42b4-b860-789999e2421a",
      "title": "桜笑み君想う",
      "artist": "白河ななか",
      "isrc": "JPI100702855",
      "releaseDate": "2008-01-23",
      "spotifyUrl": "",
      "isFallback": false
    },
    {
      "id": "3803293d-89f2-4b21-a73e-3a6adbcc9e76",
      "title": "僕らの",
      "artist": "Gero",
      "isrc": "JPPI01355860",
      "releaseDate": "2014-01-29",
      "spotifyUrl": "https://open.spotify.com/track/4yy1z06Xj7AD2i9yPIKqVR",
      "isFallback": true
    },
    {
      "id": "278f82b3-47d6-4adf-8384-8c3ca137603c",
      "title": "僕の言葉で",
      "artist": "LiSA",
      "isrc": "JPE301302677",
      "releaseDate": "2013-10-30",
      "spotifyUrl": "https://open.spotify.com/track/2oukPm9yap4g2hFtjigIw9",
      "isFallback": true
    },
    {
      "id": "f8acf1af-36bc-4f58-aaef-6bddf1e3e75a",
      "title": "ヒトカケラの勇気",
      "artist": "藍井エイル",
      "isrc": "JPU901801085",
      "releaseDate": "2018-06-13",
      "spotifyUrl": "https://open.spotify.com/track/1x6DIYGxyHTYUFgmGEd4Ey",
      "isFallback": true
    },
    {
      "id": "ce6fdf9b-b5ce-4be4-a3f8-4a70fdefa4c5",
      "title": "ドリームスペーシア",
      "artist": "栗橋みなみ",
      "isrc": "JPI100700886",
      "releaseDate": "2007-06-27",
      "spotifyUrl": "https://open.spotify.com/track/3v0CAfDf2LDSe8TM0yK7iC",
      "isFallback": true
    },
    {
      "id": "dde03031-6883-45b2-a810-c485d22d0fdc",
      "title": "不自由なEmotion",
      "artist": "美郷あき",
      "isrc": "JPI100602780",
      "releaseDate": "2007-01-24",
      "spotifyUrl": "https://open.spotify.com/track/3qgUe3DYwAkzsmRUjDL16Z",
      "isFallback": true
    },
    {
      "id": "248f5cb4-cc59-4159-9db0-4f01b39fc107",
      "title": "夢をかなえてドラえもん",
      "artist": "mao",
      "isrc": "JPCO00711340",
      "releaseDate": "2007-07-04",
      "spotifyUrl": "https://open.spotify.com/track/09j3OTkMYyk2dOfFfk3Bcx",
      "isFallback": true
    },
    {
      "id": "aa48be63-a0e4-4e41-9fe7-c84be94314b8",
      "title": "アマオト",
      "artist": "Duca",
      "isrc": "",
      "releaseDate": "2008-09-30",
      "spotifyUrl": "",
      "isFallback": false
    },
    {
      "id": "7b556299-b4bf-4f80-a129-ba3a56361368",
      "title": "チェーリング",
      "artist": "yozuca*",
      "isrc": "JPI100501120",
      "releaseDate": "2005-07-21",
      "spotifyUrl": "",
      "isFallback": false
    },
    {
      "id": "e8e5e739-a306-4abd-b8be-34f082b0c37b",
      "title": "見上げるあの空で",
      "artist": "結城アイラ",
      "isrc": "JPI100701252",
      "releaseDate": "2007-08-08",
      "spotifyUrl": "https://open.spotify.com/track/5YbrqX4jQmuZB0lpSRoo78",
      "isFallback": true
    },
    {
      "id": "20dda7f1-3052-4168-bdf9-b7fefb530378",
      "title": "流星群",
      "artist": "ジュリア",
      "isrc": "JPI101302097",
      "releaseDate": "2013-09-25",
      "spotifyUrl": "https://open.spotify.com/track/5p9K3smE2URccPO3PIr32x",
      "isFallback": false
    },
    {
      "id": "a6f6cffa-64d3-4f84-8de1-6e5280eca4ff",
      "title": "名もなき星～Silent Stars～",
      "artist": "Gero",
      "isrc": "JPPI01300080",
      "releaseDate": "2013-07-10",
      "spotifyUrl": "https://open.spotify.com/track/21I1mSsuaSTaUhwcEpU2Qw",
      "isFallback": true
    },
    {
      "id": "e71d8339-954c-4190-bd49-c5c59339985f",
      "title": "忘却バタフライ",
      "artist": "美郷あき",
      "isrc": "JPI100700511",
      "releaseDate": "2007-05-09",
      "spotifyUrl": "https://open.spotify.com/track/011P6z7iDXGhlFTy7F9xc8",
      "isFallback": true
    },
    {
      "id": "59ad1310-ff07-45de-bcbe-f4c8ba5bd50c",
      "title": "らくがきDictionary",
      "artist": "スフィア",
      "isrc": "JPI100903185",
      "releaseDate": "2009-12-23",
      "spotifyUrl": "https://open.spotify.com/track/5KNu92ACF0zrp6XunDJR1x",
      "isFallback": true
    },
    {
      "id": "a2b0ddb4-49ff-4db7-9637-134baa8a0323",
      "title": "私が哀しみの盾になる",
      "artist": "TRUE",
      "isrc": "JPI101502245",
      "releaseDate": "2015-12-23",
      "spotifyUrl": "https://open.spotify.com/track/5oQyHCHq6Sl9BFQPM1XBMH",
      "isFallback": true
    },
    {
      "id": "c561dedf-01cf-4268-9ffe-d156b652bfec",
      "title": "太陽ノック",
      "artist": "乃木坂46",
      "isrc": "JPU901501944",
      "releaseDate": "2015-07-22",
      "spotifyUrl": "https://open.spotify.com/track/5eDvZAip7hyk4zfCx9VgdU",
      "isFallback": true
    },
    {
      "id": "afed91eb-40e2-4956-a1d3-3c13a8c20845",
      "title": "君との約束を数えよう",
      "artist": "田所あずさ",
      "isrc": "JPI101501419",
      "releaseDate": "2015-09-02",
      "spotifyUrl": "https://open.spotify.com/track/2gKPuYRdVxelRWHSUbfaFp",
      "isFallback": true
    },
    {
      "id": "60282770-f960-473a-a889-a5af526f38ca",
      "title": "水色メロディ",
      "artist": "月島きらり",
      "isrc": "JPA600601485",
      "releaseDate": "2006-10-25",
      "spotifyUrl": "https://open.spotify.com/track/6u4ObvoCuCujqGoldBrgxy",
      "isFallback": true
    },
    {
      "id": "de0bb1bc-1317-42bb-9c8e-ba74ec96bdd3",
      "title": "ダイヤモンドの純度",
      "artist": "雪ノ下雪乃",
      "isrc": "JPPI02050130",
      "releaseDate": "2020-07-15",
      "spotifyUrl": "https://open.spotify.com/track/1lAM1gpXUIDNl1PkNRWvVt",
      "isFallback": true
    },
    {
      "id": "514cd05a-be2d-4437-8d0a-073f619f52ec",
      "title": "はるかのわたしへ",
      "artist": "茅原実里",
      "isrc": "JPI101600164",
      "releaseDate": "2016-04-06",
      "spotifyUrl": "https://open.spotify.com/track/78ACsygIZOu4e7V8Sovre8",
      "isFallback": true
    },
    {
      "id": "9bd2b0d6-6c5c-47bb-9f7f-d9bc781bf76b",
      "title": "ハーモナイズ・クローバー",
      "artist": "黒崎真音",
      "isrc": "JPPI01500590",
      "releaseDate": "2015-08-19",
      "spotifyUrl": "https://open.spotify.com/track/781qidlCk3Ed4f291R7NVh",
      "isFallback": true
    },
    {
      "id": "4661f3ca-ac03-4d4e-aab7-ed1413d8345e",
      "title": "雨のちキミと晴れ模様",
      "artist": "Duca",
      "isrc": "",
      "releaseDate": "2013-04-23",
      "spotifyUrl": "",
      "isFallback": false
    },
    {
      "id": "3b4718af-825a-49b5-8940-0867e60c212e",
      "title": "ふたりみらい",
      "artist": "クローバー",
      "isrc": "JPI100602324",
      "releaseDate": "2006-12-06",
      "spotifyUrl": "",
      "isFallback": false
    },
    {
      "id": "d27bca20-d9af-44e8-9e1f-543a7b6f9717",
      "title": "ツナグワタシ",
      "artist": "南條愛乃",
      "isrc": "JPPI01600800",
      "releaseDate": "2016-07-13",
      "spotifyUrl": "https://open.spotify.com/track/6BtYES2NjpM1tSaVyPTHaW",
      "isFallback": true
    },
    {
      "id": "67710c64-ca0f-4ffb-ac2c-4cf9f8fd0426",
      "title": "オレンジに染まった大空",
      "artist": "SSGIRLS",
      "isrc": "JPPI02451370",
      "releaseDate": "2024-07-10",
      "spotifyUrl": "https://open.spotify.com/track/0V0FzrZejs7QPYHRNn89s6",
      "isFallback": true
    },
    {
      "id": "6e97a291-2199-45a1-906d-4868a2d24a3f",
      "title": "甘やかなあした",
      "artist": "橋本みゆき",
      "isrc": "JPI100602019",
      "releaseDate": "2006-10-25",
      "spotifyUrl": "https://open.spotify.com/track/0tmzNz5BB8XJIf3G3GR4zY",
      "isFallback": true
    },
    {
      "id": "fa1f763d-7f89-46bc-98cd-89455c6222c5",
      "title": "終わらない世界",
      "artist": "mao",
      "isrc": "JPV200990103",
      "releaseDate": "2010-07-07",
      "spotifyUrl": "https://open.spotify.com/track/047Cj3HaYyDNgG9cAtDQ19",
      "isFallback": true
    },
    {
      "id": "f478e757-4078-4abd-87f6-f95abc579678",
      "title": "いつかのわたしへ",
      "artist": "茅原実里",
      "isrc": "JPI101600152",
      "releaseDate": "2016-04-06",
      "spotifyUrl": "https://open.spotify.com/track/6lw6BwteA0TTqUzk00oU7Y",
      "isFallback": true
    },
    {
      "id": "eebd7ae7-5e2e-432f-8f1b-7d02c4be518b",
      "title": "サテライト",
      "artist": "藍井エイル",
      "isrc": "JPU901202102",
      "releaseDate": "2013-01-30",
      "spotifyUrl": "https://open.spotify.com/track/6JVhxrEMzT2mWSNHWMhwFZ",
      "isFallback": true
    },
    {
      "id": "85b32c6a-eb4d-4a58-8dda-baf8ce79d08a",
      "title": "エブリデイ is パーフェクト",
      "artist": "雪ノ下雪乃",
      "isrc": "JPPI02050430",
      "releaseDate": "2020-11-27",
      "spotifyUrl": "https://open.spotify.com/track/19q3N7MdyByCoJgFUfceSU",
      "isFallback": true
    },
    {
      "id": "675bd23e-60ab-4b96-9602-eec87d39c83d",
      "title": "ここにあったね",
      "artist": "栗林みな実",
      "isrc": "JPI100801967",
      "releaseDate": "2008-10-22",
      "spotifyUrl": "https://open.spotify.com/track/7wJaI3qCZONfc23IRD1z3w",
      "isFallback": true
    },
    {
      "id": "7e9e816e-70d1-42d6-8464-052d9e9459e8",
      "title": "いつかの手紙",
      "artist": "LiSA",
      "isrc": "JPE301201901",
      "releaseDate": "2012-08-08",
      "spotifyUrl": "https://open.spotify.com/track/1yvzpPi0nTyvUnkhCZrtSP",
      "isFallback": true
    },
    {
      "id": "16e5d689-0d25-4867-9937-eeaf69a61495",
      "title": "君と私と想いの先へ",
      "artist": "野川さくら",
      "isrc": "JPI100701189",
      "releaseDate": "2007-08-01",
      "spotifyUrl": "",
      "isFallback": false
    },
    {
      "id": "10ee64a7-1494-4d3d-a03a-e26814de7863",
      "title": "ぐるぐるカーテン",
      "artist": "乃木坂46",
      "isrc": "JPSR01200121",
      "releaseDate": "2012-02-22",
      "spotifyUrl": "https://open.spotify.com/track/7jhhXXvjfuTdUS8gUSHKOk",
      "isFallback": true
    },
    {
      "id": "c3eb107e-7779-4be4-a8c5-d6d6e96a28dc",
      "title": "シンプル",
      "artist": "南條愛乃",
      "isrc": "JPPI02204260",
      "releaseDate": "2022-12-21",
      "spotifyUrl": "https://open.spotify.com/track/0uVvxLSN1G6cC0WR8ZRat0",
      "isFallback": true
    },
    {
      "id": "b2ca01c9-06cd-4510-b839-1ac0c7f663a0",
      "title": "愛にピアス",
      "artist": "板野友美",
      "isrc": "JPKI01113000",
      "releaseDate": "2011-06-01",
      "spotifyUrl": "https://open.spotify.com/track/0YLbs281zySf5AKmLaJzfK",
      "isFallback": true
    },
    {
      "id": "b877443c-907a-4670-b853-7c8fb071a2aa",
      "title": "Cross over",
      "artist": "岬なこ",
      "isrc": "JPI102503548",
      "releaseDate": "2026-01-14",
      "spotifyUrl": "https://open.spotify.com/track/1Fb8Nm3EOreoA1s8S3lW7W",
      "isFallback": true
    }
  ]
}
